weather_gov/__init__.py
weather_gov/endpoints.py
weather_gov/validations.py
weather_gov-0.2.dist-info/LICENSE
weather_gov-0.2.dist-info/METADATA
weather_gov-0.2.dist-info/WHEEL
weather_gov-0.2.dist-info/top_level.txt
weather_gov-0.2.dist-info/RECORD
