Metadata-Version: 2.1
Name: weather-gov
Version: 0.2
Summary: A Python wrapper for the National Weather Service's Weather.gov API
Home-page: https://github.com/spectrshiv/python-weather_gov
Author: TJ Courier
Author-email: pycepticus@gmail.com
Classifier: Programming Language :: Python :: 3
Classifier: License :: OSI Approved :: GNU General Public License v3 (GPLv3)
Classifier: Operating System :: OS Independent
Classifier: Development Status :: 2 - Pre-Alpha
Classifier: Intended Audience :: Developers
Classifier: Intended Audience :: Science/Research
Classifier: Topic :: Scientific/Engineering :: Atmospheric Science
License-File: LICENSE
